quantity_array/__init__.py
quantity_array-0.0.1.dist-info/METADATA
quantity_array-0.0.1.dist-info/WHEEL
quantity_array-0.0.1.dist-info/licenses/LICENSE
quantity_array-0.0.1.dist-info/RECORD
